dash_flex_layout/DashFlexLayout.py
dash_flex_layout/PanelWrapper.py
dash_flex_layout/Tab.py
dash_flex_layout/__init__.py
dash_flex_layout/_imports_.py
dash_flex_layout/dash_flex_layout.min.js
dash_flex_layout/dash_flex_layout.min.js.map
dash_flex_layout/metadata.json
dash_flex_layout/package-info.json
flexlayout_dash-1.0.0.dist-info/licenses/LICENSE
flexlayout_dash-1.0.0.dist-info/METADATA
flexlayout_dash-1.0.0.dist-info/WHEEL
flexlayout_dash-1.0.0.dist-info/top_level.txt
flexlayout_dash-1.0.0.dist-info/RECORD
