Metadata-Version: 2.4
Name: flexlayout_dash
Version: 1.0.0
Summary: Flexible docking layout system for Dash applications
Author: Pip Install Python <pipinstallpython@gmail.com>
License: MIT
Classifier: Framework :: Dash
License-File: LICENSE
Dynamic: author
Dynamic: classifier
Dynamic: description
Dynamic: description-content-type
Dynamic: license
Dynamic: license-file
Dynamic: summary
